{"targets": [{"isStage": true, "name": "Stage", "variables": {}, "lists": {}, "broadcasts": {}, "blocks": {}, "comments": {}, "currentCostume": 0, "costumes": [{"assetId": "4f1a1e4e4d182393270fa1b546b7d902", "name": "\u65b9\u5757\u8349\u576a", "bitmapResolution": 2, "md5ext": "4f1a1e4e4d182393270fa1b546b7d902.png", "dataFormat": "png", "rotationCenterX": 480, "rotationCenterY": 360}], "sounds": [{"assetId": "83a9787d4cb6f3b7632b4ddfebf74367", "name": "\u5575", "dataFormat": "wav", "format": "", "rate": 48000, "sampleCount": 1123, "md5ext": "83a9787d4cb6f3b7632b4ddfebf74367.wav"}], "volume": 100, "layerOrder": 0, "tempo": 60, "videoTransparency": 50, "videoState": "off", "textToSpeechLanguage": null}, {"isStage": false, "name": "\u6bd4\u5c14", "variables": {}, "lists": {}, "broadcasts": {}, "blocks": {"3F![:$M!Ke@@k4NStc7q": {"opcode": "event_whenflagclicked", "next": "S:{t_Pyy/-[,%3)Zjs+;", "parent": null, "inputs": {}, "fields": {}, "shadow": false, "topLevel": true, "x": 280, "y": 142}, "S!`906Fsa?@b9@o}#L%L": {"opcode": "motion_gotoxy", "next": "$.SCrsyP,iUXk}L3.xIx", "parent": "S:{t_Pyy/-[,%3)Zjs+;", "inputs": {"X": [1, [4, "-130"]], "Y": [1, [4, "-160"]]}, "fields": {}, "shadow": false, "topLevel": false}, "$.SCrsyP,iUXk}L3.xIx": {"opcode": "control_forever", "next": null, "parent": "S!`906Fsa?@b9@o}#L%L", "inputs": {"SUBSTACK": [2, "6vB.WY.d#_n6HRLywg0K"]}, "fields": {}, "shadow": false, "topLevel": false}, "6vB.WY.d#_n6HRLywg0K": {"opcode": "control_if", "next": "x0$?2-vN4r;W+2$`6wol", "parent": "$.SCrsyP,iUXk}L3.xIx", "inputs": {"CONDITION": [2, "}9jSTaNr^T08E}B~G;E["], "SUBSTACK": [2, "4a~~?qxOQM,d$%)=!(3F"]}, "fields": {}, "shadow": false, "topLevel": false}, "}9jSTaNr^T08E}B~G;E[": {"opcode": "sensing_keypressed", "next": null, "parent": "6vB.WY.d#_n6HRLywg0K", "inputs": {"KEY_OPTION": [1, "0z!+FEGwV`ZWNGL[C_YW"]}, "fields": {}, "shadow": false, "topLevel": false}, "0z!+FEGwV`ZWNGL[C_YW": {"opcode": "sensing_keyoptions", "next": null, "parent": "}9jSTaNr^T08E}B~G;E[", "inputs": {}, "fields": {"KEY_OPTION": ["right arrow", null]}, "shadow": true, "topLevel": false}, "4a~~?qxOQM,d$%)=!(3F": {"opcode": "looks_switchcostumeto", "next": "$DM]]7#*:.{U{3BX}}si", "parent": "6vB.WY.d#_n6HRLywg0K", "inputs": {"COSTUME": [1, "kvjwZydR;,FpRX?S1Be~"]}, "fields": {}, "shadow": false, "topLevel": false}, "kvjwZydR;,FpRX?S1Be~": {"opcode": "looks_costume", "next": null, "parent": "4a~~?qxOQM,d$%)=!(3F", "inputs": {}, "fields": {"COSTUME": ["\u53f3\u4fa7", null]}, "shadow": true, "topLevel": false}, "$DM]]7#*:.{U{3BX}}si": {"opcode": "motion_changexby", "next": null, "parent": "4a~~?qxOQM,d$%)=!(3F", "inputs": {"DX": [1, [4, "10"]]}, "fields": {}, "shadow": false, "topLevel": false}, "S:{t_Pyy/-[,%3)Zjs+;": {"opcode": "looks_switchcostumeto", "next": "S!`906Fsa?@b9@o}#L%L", "parent": "3F![:$M!Ke@@k4NStc7q", "inputs": {"COSTUME": [1, "xa$c]3La:VM7w$pJ]*PA"]}, "fields": {}, "shadow": false, "topLevel": false}, "xa$c]3La:VM7w$pJ]*PA": {"opcode": "looks_costume", "next": null, "parent": "S:{t_Pyy/-[,%3)Zjs+;", "inputs": {}, "fields": {"COSTUME": ["\u6b63\u9762", null]}, "shadow": true, "topLevel": false}, "x0$?2-vN4r;W+2$`6wol": {"opcode": "control_if", "next": "L^c8u;BTB|q7]dYE9XRI", "parent": "6vB.WY.d#_n6HRLywg0K", "inputs": {"CONDITION": [2, "c|N7#NbuBmrKx9|x*NEn"], "SUBSTACK": [2, "JOXvUF8lRI#zw0Yl*H7o"]}, "fields": {}, "shadow": false, "topLevel": false}, "c|N7#NbuBmrKx9|x*NEn": {"opcode": "sensing_keypressed", "next": null, "parent": "x0$?2-vN4r;W+2$`6wol", "inputs": {"KEY_OPTION": [1, "N04Ocq1YEkFXMO4SDB@%"]}, "fields": {}, "shadow": false, "topLevel": false}, "N04Ocq1YEkFXMO4SDB@%": {"opcode": "sensing_keyoptions", "next": null, "parent": "c|N7#NbuBmrKx9|x*NEn", "inputs": {}, "fields": {"KEY_OPTION": ["left arrow", null]}, "shadow": true, "topLevel": false}, "JOXvUF8lRI#zw0Yl*H7o": {"opcode": "looks_switchcostumeto", "next": "Iv@TEE*6QqjJnym94/+!", "parent": "x0$?2-vN4r;W+2$`6wol", "inputs": {"COSTUME": [1, "-qoHZ5w^49aEiiVAOMFt"]}, "fields": {}, "shadow": false, "topLevel": false}, "-qoHZ5w^49aEiiVAOMFt": {"opcode": "looks_costume", "next": null, "parent": "JOXvUF8lRI#zw0Yl*H7o", "inputs": {}, "fields": {"COSTUME": ["\u5de6\u4fa7", null]}, "shadow": true, "topLevel": false}, "Iv@TEE*6QqjJnym94/+!": {"opcode": "motion_changexby", "next": null, "parent": "JOXvUF8lRI#zw0Yl*H7o", "inputs": {"DX": [1, [4, "-10"]]}, "fields": {}, "shadow": false, "topLevel": false}, "L^c8u;BTB|q7]dYE9XRI": {"opcode": "control_if", "next": "536-/ukmN?dezx];y(_m", "parent": "x0$?2-vN4r;W+2$`6wol", "inputs": {"CONDITION": [2, "qlmtKW4{fT,-f(07;jrx"], "SUBSTACK": [2, "7Dn|ba6/!YK`fB%*2{eX"]}, "fields": {}, "shadow": false, "topLevel": false}, "qlmtKW4{fT,-f(07;jrx": {"opcode": "sensing_keypressed", "next": null, "parent": "L^c8u;BTB|q7]dYE9XRI", "inputs": {"KEY_OPTION": [1, "0+qR+j)[3YHqcBsWpC,I"]}, "fields": {}, "shadow": false, "topLevel": false}, "0+qR+j)[3YHqcBsWpC,I": {"opcode": "sensing_keyoptions", "next": null, "parent": "qlmtKW4{fT,-f(07;jrx", "inputs": {}, "fields": {"KEY_OPTION": ["up arrow", null]}, "shadow": true, "topLevel": false}, "7Dn|ba6/!YK`fB%*2{eX": {"opcode": "looks_switchcostumeto", "next": "pqE9qjE:~B@N1+G#iC*D", "parent": "L^c8u;BTB|q7]dYE9XRI", "inputs": {"COSTUME": [1, "t4dm/7D_v`=]d*iY5.hU"]}, "fields": {}, "shadow": false, "topLevel": false}, "t4dm/7D_v`=]d*iY5.hU": {"opcode": "looks_costume", "next": null, "parent": "7Dn|ba6/!YK`fB%*2{eX", "inputs": {}, "fields": {"COSTUME": ["\u80cc\u9762", null]}, "shadow": true, "topLevel": false}, "pqE9qjE:~B@N1+G#iC*D": {"opcode": "motion_changeyby", "next": null, "parent": "7Dn|ba6/!YK`fB%*2{eX", "inputs": {"DY": [1, [4, "10"]]}, "fields": {}, "shadow": false, "topLevel": false}, "536-/ukmN?dezx];y(_m": {"opcode": "control_if", "next": null, "parent": "L^c8u;BTB|q7]dYE9XRI", "inputs": {"CONDITION": [2, "-/B~nCKH%z/Rje@GHco0"], "SUBSTACK": [2, "z_yKx6M;14Gd68wV%pW^"]}, "fields": {}, "shadow": false, "topLevel": false}, "-/B~nCKH%z/Rje@GHco0": {"opcode": "sensing_keypressed", "next": null, "parent": "536-/ukmN?dezx];y(_m", "inputs": {"KEY_OPTION": [1, "9t#PxZg|RwJlg18xSW{Y"]}, "fields": {}, "shadow": false, "topLevel": false}, "9t#PxZg|RwJlg18xSW{Y": {"opcode": "sensing_keyoptions", "next": null, "parent": "-/B~nCKH%z/Rje@GHco0", "inputs": {}, "fields": {"KEY_OPTION": ["down arrow", null]}, "shadow": true, "topLevel": false}, "z_yKx6M;14Gd68wV%pW^": {"opcode": "looks_switchcostumeto", "next": "f3fo[u3)Rdl?P(jBi~*R", "parent": "536-/ukmN?dezx];y(_m", "inputs": {"COSTUME": [1, "i;|cO~-LAVitqS[*cwU%"]}, "fields": {}, "shadow": false, "topLevel": false}, "i;|cO~-LAVitqS[*cwU%": {"opcode": "looks_costume", "next": null, "parent": "z_yKx6M;14Gd68wV%pW^", "inputs": {}, "fields": {"COSTUME": ["\u6b63\u9762", null]}, "shadow": true, "topLevel": false}, "f3fo[u3)Rdl?P(jBi~*R": {"opcode": "motion_changeyby", "next": null, "parent": "z_yKx6M;14Gd68wV%pW^", "inputs": {"DY": [1, [4, "-10"]]}, "fields": {}, "shadow": false, "topLevel": false}}, "comments": {}, "currentCostume": 0, "costumes": [{"assetId": "6d5c2f4220d31d77923556ddadbe2cb7", "name": "\u6b63\u9762", "bitmapResolution": 2, "md5ext": "6d5c2f4220d31d77923556ddadbe2cb7.png", "dataFormat": "png", "rotationCenterX": 408, "rotationCenterY": 306}, {"assetId": "5500fa153f15ad0654b9b5ee5e8cb60b", "name": "\u80cc\u9762", "bitmapResolution": 2, "md5ext": "5500fa153f15ad0654b9b5ee5e8cb60b.png", "dataFormat": "png", "rotationCenterX": 408, "rotationCenterY": 306}, {"assetId": "75704083eb3f861c7ab4446f146fa210", "name": "\u5de6\u4fa7", "bitmapResolution": 2, "md5ext": "75704083eb3f861c7ab4446f146fa210.png", "dataFormat": "png", "rotationCenterX": 408, "rotationCenterY": 306}, {"assetId": "0ae758003b05092e479bcc28ef18a68a", "name": "\u53f3\u4fa7", "bitmapResolution": 2, "md5ext": "0ae758003b05092e479bcc28ef18a68a.png", "dataFormat": "png", "rotationCenterX": 408, "rotationCenterY": 306}], "sounds": [], "volume": 100, "layerOrder": 1, "visible": true, "x": -130, "y": -160, "size": 100, "direction": 91.02862060759102, "draggable": false, "rotationStyle": "all around"}, {"isStage": false, "name": "\u65b9\u5757\u517d", "variables": {}, "lists": {}, "broadcasts": {}, "blocks": {"^loF+x!u(1}7iG$UJt@X": {"opcode": "event_whenflagclicked", "next": "J`CNXoj@Y_xop$roz2wO", "parent": null, "inputs": {}, "fields": {}, "shadow": false, "topLevel": true, "x": 195, "y": 124}, "J`CNXoj@Y_xop$roz2wO": {"opcode": "motion_gotoxy", "next": "?-z?^R(YN0L@}$`X)~Bm", "parent": "^loF+x!u(1}7iG$UJt@X", "inputs": {"X": [1, [4, "133"]], "Y": [1, [4, "157"]]}, "fields": {}, "shadow": false, "topLevel": false}, "?-z?^R(YN0L@}$`X)~Bm": {"opcode": "control_forever", "next": null, "parent": "J`CNXoj@Y_xop$roz2wO", "inputs": {"SUBSTACK": [2, "37TXlX8wNOEyB}vp^oB)"]}, "fields": {}, "shadow": false, "topLevel": false}, "?Xkw9H798M19FSY45G1]": {"opcode": "motion_movesteps", "next": "TS]zYTT,j~hy?gvhLA0s", "parent": "37TXlX8wNOEyB}vp^oB)", "inputs": {"STEPS": [1, [4, "2"]]}, "fields": {}, "shadow": false, "topLevel": false}, "37TXlX8wNOEyB}vp^oB)": {"opcode": "motion_pointtowards", "next": "?Xkw9H798M19FSY45G1]", "parent": "?-z?^R(YN0L@}$`X)~Bm", "inputs": {"TOWARDS": [1, "t+_Ve;jdBR}:x*O*e{dX"]}, "fields": {}, "shadow": false, "topLevel": false}, "t+_Ve;jdBR}:x*O*e{dX": {"opcode": "motion_pointtowards_menu", "next": null, "parent": "37TXlX8wNOEyB}vp^oB)", "inputs": {}, "fields": {"TOWARDS": ["\u6bd4\u5c14", null]}, "shadow": true, "topLevel": false}, "TS]zYTT,j~hy?gvhLA0s": {"opcode": "control_if", "next": null, "parent": "?Xkw9H798M19FSY45G1]", "inputs": {"CONDITION": [2, "}cJItrFnfCx52zp%M,g0"], "SUBSTACK": [2, "*~nzq9aFn{!.[d~@^n:l"]}, "fields": {}, "shadow": false, "topLevel": false}, "}cJItrFnfCx52zp%M,g0": {"opcode": "sensing_touchingobject", "next": null, "parent": "TS]zYTT,j~hy?gvhLA0s", "inputs": {"TOUCHINGOBJECTMENU": [1, "%f{M.q_`ZK7)F45x=Da+"]}, "fields": {}, "shadow": false, "topLevel": false}, "%f{M.q_`ZK7)F45x=Da+": {"opcode": "sensing_touchingobjectmenu", "next": null, "parent": "}cJItrFnfCx52zp%M,g0", "inputs": {}, "fields": {"TOUCHINGOBJECTMENU": ["\u6bd4\u5c14", null]}, "shadow": true, "topLevel": false}, "*~nzq9aFn{!.[d~@^n:l": {"opcode": "control_stop", "next": null, "parent": "TS]zYTT,j~hy?gvhLA0s", "inputs": {}, "fields": {"STOP_OPTION": ["all", null]}, "shadow": false, "topLevel": false, "mutation": {"tagName": "mutation", "children": [], "hasnext": "false"}}}, "comments": {}, "currentCostume": 0, "costumes": [{"assetId": "793671f9aa1603ca2a25673a08dbb2f9", "name": "\u65b9\u5757\u517d", "bitmapResolution": 1, "md5ext": "793671f9aa1603ca2a25673a08dbb2f9.svg", "dataFormat": "svg", "rotationCenterX": 16, "rotationCenterY": 23}], "sounds": [], "volume": 100, "layerOrder": 2, "visible": true, "x": -114.74237835755349, "y": -141.60963475035916, "size": 100, "direction": -140.3191009076131, "draggable": false, "rotationStyle": "left-right"}], "monitors": [], "extensions": [], "meta": {"semver": "3.0.0", "vm": "0.2.0-prerelease.20190524155459", "agent": "Mozilla/5.0 (Windows NT 10.0; WOW64) AppleWebKit/537.36 (KHTML, like Gecko) Chrome/63.0.3239.132 Safari/537.36"}}