{"targets": [{"isStage": true, "name": "Stage", "variables": {}, "lists": {}, "broadcasts": {}, "blocks": {}, "comments": {}, "currentCostume": 0, "costumes": [{"assetId": "4f1a1e4e4d182393270fa1b546b7d902", "name": "\u65b9\u5757\u8349\u576a", "bitmapResolution": 2, "md5ext": "4f1a1e4e4d182393270fa1b546b7d902.png", "dataFormat": "png", "rotationCenterX": 480, "rotationCenterY": 360}], "sounds": [{"assetId": "83a9787d4cb6f3b7632b4ddfebf74367", "name": "\u5575", "dataFormat": "wav", "format": "", "rate": 48000, "sampleCount": 1123, "md5ext": "83a9787d4cb6f3b7632b4ddfebf74367.wav"}], "volume": 100, "layerOrder": 0, "tempo": 60, "videoTransparency": 50, "videoState": "off", "textToSpeechLanguage": null}, {"isStage": false, "name": "\u6b66\u5668", "variables": {}, "lists": {}, "broadcasts": {}, "blocks": {"jrsGSl_dqO3gA3Jj]n[S": {"opcode": "event_whenkeypressed", "next": "sXv[F.jt5*yL}:n6k5e7", "parent": null, "inputs": {}, "fields": {"KEY_OPTION": ["k", null]}, "shadow": false, "topLevel": true, "x": 239, "y": 89}, "sXv[F.jt5*yL}:n6k5e7": {"opcode": "looks_nextcostume", "next": "dTf0qFkc.{eNEx.qw`/h", "parent": "jrsGSl_dqO3gA3Jj]n[S", "inputs": {}, "fields": {}, "shadow": false, "topLevel": false}, "Zt|!5/BA@]Q8uF,3r^xf": {"opcode": "event_whenflagclicked", "next": "sp7Z*.RYw~.e%KLq*AGm", "parent": null, "inputs": {}, "fields": {}, "shadow": false, "topLevel": true, "x": 35, "y": -265}, "sp7Z*.RYw~.e%KLq*AGm": {"opcode": "control_forever", "next": null, "parent": "Zt|!5/BA@]Q8uF,3r^xf", "inputs": {"SUBSTACK": [2, "7R@^Q(]ghRI0_5(PFGIa"]}, "fields": {}, "shadow": false, "topLevel": false}, "7R@^Q(]ghRI0_5(PFGIa": {"opcode": "motion_pointindirection", "next": "_W`DtLQL(,J?fk;H!e*4", "parent": "sp7Z*.RYw~.e%KLq*AGm", "inputs": {"DIRECTION": [3, "_}-9$tDX4)09`sxS#Gg#", [8, "90"]]}, "fields": {}, "shadow": false, "topLevel": false}, "_}-9$tDX4)09`sxS#Gg#": {"opcode": "sensing_of", "next": null, "parent": "7R@^Q(]ghRI0_5(PFGIa", "inputs": {"OBJECT": [1, "_/U[fc$PCkakh)/)MB;u"]}, "fields": {"PROPERTY": ["direction", null]}, "shadow": false, "topLevel": false}, "_/U[fc$PCkakh)/)MB;u": {"opcode": "sensing_of_object_menu", "next": null, "parent": "_}-9$tDX4)09`sxS#Gg#", "inputs": {}, "fields": {"OBJECT": ["\u6bd4\u5c14", null]}, "shadow": true, "topLevel": false}, "_W`DtLQL(,J?fk;H!e*4": {"opcode": "motion_goto", "next": null, "parent": "7R@^Q(]ghRI0_5(PFGIa", "inputs": {"TO": [1, "8RGoY]0VzN`Q73y:?04z"]}, "fields": {}, "shadow": false, "topLevel": false}, "8RGoY]0VzN`Q73y:?04z": {"opcode": "motion_goto_menu", "next": null, "parent": "_W`DtLQL(,J?fk;H!e*4", "inputs": {}, "fields": {"TO": ["\u6bd4\u5c14", null]}, "shadow": true, "topLevel": false}, "ltnPiC-9uB@rQ0GQ|X8!": {"opcode": "looks_switchcostumeto", "next": null, "parent": "dTf0qFkc.{eNEx.qw`/h", "inputs": {"COSTUME": [1, "9+RZ+Ur%uV+32]~rE^*g"]}, "fields": {}, "shadow": false, "topLevel": false}, "9+RZ+Ur%uV+32]~rE^*g": {"opcode": "looks_costume", "next": null, "parent": "ltnPiC-9uB@rQ0GQ|X8!", "inputs": {}, "fields": {"COSTUME": ["\u6b66\u56682", null]}, "shadow": true, "topLevel": false}, "dTf0qFkc.{eNEx.qw`/h": {"opcode": "control_wait", "next": "ltnPiC-9uB@rQ0GQ|X8!", "parent": "sXv[F.jt5*yL}:n6k5e7", "inputs": {"DURATION": [1, [5, "0"]]}, "fields": {}, "shadow": false, "topLevel": false}, "h1T3FE3GztXA:FZ{j,^]": {"opcode": "looks_nextcostume", "next": "fj[1gqN%.y[kCOIz#rHN", "parent": "@I,t5To}7@}rNgUxvw8R", "inputs": {}, "fields": {}, "shadow": false, "topLevel": false}, "fj[1gqN%.y[kCOIz#rHN": {"opcode": "control_wait", "next": "/6n[81M~(OqiOy2Qz$)R", "parent": "h1T3FE3GztXA:FZ{j,^]", "inputs": {"DURATION": [1, [5, "0"]]}, "fields": {}, "shadow": false, "topLevel": false}, "/6n[81M~(OqiOy2Qz$)R": {"opcode": "looks_switchcostumeto", "next": null, "parent": "fj[1gqN%.y[kCOIz#rHN", "inputs": {"COSTUME": [1, "OkCB{7`!@Zqa672PY.JO"]}, "fields": {}, "shadow": false, "topLevel": false}, "OkCB{7`!@Zqa672PY.JO": {"opcode": "looks_costume", "next": null, "parent": "/6n[81M~(OqiOy2Qz$)R", "inputs": {}, "fields": {"COSTUME": ["\u6b66\u56683", null]}, "shadow": true, "topLevel": false}, "@I,t5To}7@}rNgUxvw8R": {"opcode": "event_whenkeypressed", "next": "h1T3FE3GztXA:FZ{j,^]", "parent": null, "inputs": {}, "fields": {"KEY_OPTION": ["l", null]}, "shadow": false, "topLevel": true, "x": 431, "y": 87}, "8]Vii9:r%A-WorC#vOx~": {"opcode": "event_whenkeypressed", "next": "rz`@(Pb6iT.QdI2c~Z3,", "parent": null, "inputs": {}, "fields": {"KEY_OPTION": ["j", null]}, "shadow": false, "topLevel": true, "x": 41, "y": 87}, "rz`@(Pb6iT.QdI2c~Z3,": {"opcode": "looks_nextcostume", "next": "F?@;$(BTk/c,x77+|G|O", "parent": "8]Vii9:r%A-WorC#vOx~", "inputs": {}, "fields": {}, "shadow": false, "topLevel": false}, "F?@;$(BTk/c,x77+|G|O": {"opcode": "control_wait", "next": "Xm=V:Y`;8uUf.Q/o(?_j", "parent": "rz`@(Pb6iT.QdI2c~Z3,", "inputs": {"DURATION": [1, [5, "0"]]}, "fields": {}, "shadow": false, "topLevel": false}, "Xm=V:Y`;8uUf.Q/o(?_j": {"opcode": "looks_switchcostumeto", "next": null, "parent": "F?@;$(BTk/c,x77+|G|O", "inputs": {"COSTUME": [1, "QilMk(/S|.@56@mbg6z^"]}, "fields": {}, "shadow": false, "topLevel": false}, "QilMk(/S|.@56@mbg6z^": {"opcode": "looks_costume", "next": null, "parent": "Xm=V:Y`;8uUf.Q/o(?_j", "inputs": {}, "fields": {"COSTUME": ["\u6b66\u56681", null]}, "shadow": true, "topLevel": false}}, "comments": {}, "currentCostume": 0, "costumes": [{"assetId": "c451d2c22d1fad8d70b4655fff0fe2bb", "name": "\u6b66\u56681", "bitmapResolution": 2, "md5ext": "c451d2c22d1fad8d70b4655fff0fe2bb.png", "dataFormat": "png", "rotationCenterX": 408, "rotationCenterY": 306}, {"assetId": "579a12d0122398f24d9943dad508b5dd", "name": "\u6b66\u56682", "bitmapResolution": 2, "md5ext": "579a12d0122398f24d9943dad508b5dd.png", "dataFormat": "png", "rotationCenterX": 408, "rotationCenterY": 306}, {"assetId": "ac99a03e8b7aec8c8fd80b2d5290b637", "name": "\u6b66\u56683", "bitmapResolution": 2, "md5ext": "ac99a03e8b7aec8c8fd80b2d5290b637.png", "dataFormat": "png", "rotationCenterX": 408, "rotationCenterY": 306}], "sounds": [], "volume": 100, "layerOrder": 2, "visible": true, "x": -175, "y": -63, "size": 100, "direction": 180, "draggable": true, "rotationStyle": "all around"}, {"isStage": false, "name": "\u6bd4\u5c14", "variables": {}, "lists": {}, "broadcasts": {}, "blocks": {"j4Bo:V~=:uri+TnQl=.N": {"opcode": "event_whenflagclicked", "next": "NCY4k7U){Udv-Ydo=@Zg", "parent": null, "inputs": {}, "fields": {}, "shadow": false, "topLevel": true, "x": 98, "y": 105}, "aUgwl7hUHzmrR5pl]2xi": {"opcode": "motion_setrotationstyle", "next": null, "parent": "NCY4k7U){Udv-Ydo=@Zg", "inputs": {}, "fields": {"STYLE": ["don't rotate", null]}, "shadow": false, "topLevel": false}, "NCY4k7U){Udv-Ydo=@Zg": {"opcode": "motion_gotoxy", "next": "aUgwl7hUHzmrR5pl]2xi", "parent": "j4Bo:V~=:uri+TnQl=.N", "inputs": {"X": [1, [4, "-195"]], "Y": [1, [4, "-133"]]}, "fields": {}, "shadow": false, "topLevel": false}, "BX,E^JUO=*G5~B5,$pY1": {"opcode": "event_whenkeypressed", "next": "B,kFCA8b8R{a4ObSr?d=", "parent": null, "inputs": {}, "fields": {"KEY_OPTION": ["up arrow", null]}, "shadow": false, "topLevel": true, "x": 95, "y": 289}, "_r,I3Z@rdn`Alq_sLkDS": {"opcode": "motion_movesteps", "next": null, "parent": "6|J(mIh|+X#a,mV%Xv/I", "inputs": {"STEPS": [1, [4, "10"]]}, "fields": {}, "shadow": false, "topLevel": false}, "6|J(mIh|+X#a,mV%Xv/I": {"opcode": "looks_switchcostumeto", "next": "_r,I3Z@rdn`Alq_sLkDS", "parent": "B,kFCA8b8R{a4ObSr?d=", "inputs": {"COSTUME": [1, "IgkDX*BwSfi(wtp:PQ5I"]}, "fields": {}, "shadow": false, "topLevel": false}, "IgkDX*BwSfi(wtp:PQ5I": {"opcode": "looks_costume", "next": null, "parent": "6|J(mIh|+X#a,mV%Xv/I", "inputs": {}, "fields": {"COSTUME": ["\u80cc\u9762", null]}, "shadow": true, "topLevel": false}, "B,kFCA8b8R{a4ObSr?d=": {"opcode": "motion_pointindirection", "next": "6|J(mIh|+X#a,mV%Xv/I", "parent": "BX,E^JUO=*G5~B5,$pY1", "inputs": {"DIRECTION": [1, [8, "0"]]}, "fields": {}, "shadow": false, "topLevel": false}, "_|yC|!(fBqa/~S_tOo4I": {"opcode": "event_whenkeypressed", "next": "klG7I,+73T(EzfjXc|yD", "parent": null, "inputs": {}, "fields": {"KEY_OPTION": ["down arrow", null]}, "shadow": false, "topLevel": true, "x": 383, "y": 295}, "klG7I,+73T(EzfjXc|yD": {"opcode": "motion_pointindirection", "next": "Tp5?^)?bniKz/gY@c9(i", "parent": "_|yC|!(fBqa/~S_tOo4I", "inputs": {"DIRECTION": [1, [8, "180"]]}, "fields": {}, "shadow": false, "topLevel": false}, "Tp5?^)?bniKz/gY@c9(i": {"opcode": "looks_switchcostumeto", "next": "m9xNvq9Xgk{C{/Lb/JL3", "parent": "klG7I,+73T(EzfjXc|yD", "inputs": {"COSTUME": [1, "+E4}Dsiz{9rc;;bDFJBd"]}, "fields": {}, "shadow": false, "topLevel": false}, "+E4}Dsiz{9rc;;bDFJBd": {"opcode": "looks_costume", "next": null, "parent": "Tp5?^)?bniKz/gY@c9(i", "inputs": {}, "fields": {"COSTUME": ["\u6b63\u9762", null]}, "shadow": true, "topLevel": false}, "m9xNvq9Xgk{C{/Lb/JL3": {"opcode": "motion_movesteps", "next": null, "parent": "Tp5?^)?bniKz/gY@c9(i", "inputs": {"STEPS": [1, [4, "10"]]}, "fields": {}, "shadow": false, "topLevel": false}, "I}}fS]m1-P@iahyAuLj]": {"opcode": "motion_pointindirection", "next": "NEfkOWK5}6BiRT|4[MD(", "parent": "5$nY$p[ufQBCy}z2%AEN", "inputs": {"DIRECTION": [1, [8, "-90"]]}, "fields": {}, "shadow": false, "topLevel": false}, "NEfkOWK5}6BiRT|4[MD(": {"opcode": "looks_switchcostumeto", "next": "r/h;?Zj1*0RKVp9pJTj$", "parent": "I}}fS]m1-P@iahyAuLj]", "inputs": {"COSTUME": [1, "$pt=BD(WBEVAOL[:mww~"]}, "fields": {}, "shadow": false, "topLevel": false}, "$pt=BD(WBEVAOL[:mww~": {"opcode": "looks_costume", "next": null, "parent": "NEfkOWK5}6BiRT|4[MD(", "inputs": {}, "fields": {"COSTUME": ["\u5de6\u4fa7", null]}, "shadow": true, "topLevel": false}, "r/h;?Zj1*0RKVp9pJTj$": {"opcode": "motion_movesteps", "next": null, "parent": "NEfkOWK5}6BiRT|4[MD(", "inputs": {"STEPS": [1, [4, "10"]]}, "fields": {}, "shadow": false, "topLevel": false}, "5$nY$p[ufQBCy}z2%AEN": {"opcode": "event_whenkeypressed", "next": "I}}fS]m1-P@iahyAuLj]", "parent": null, "inputs": {}, "fields": {"KEY_OPTION": ["left arrow", null]}, "shadow": false, "topLevel": true, "x": 87, "y": 525}, "/8H/QPflcfn0ek?VmU+l": {"opcode": "event_whenkeypressed", "next": "-7aR[iFx%+mv;@OMn3ld", "parent": null, "inputs": {}, "fields": {"KEY_OPTION": ["right arrow", null]}, "shadow": false, "topLevel": true, "x": 373, "y": 523}, "-7aR[iFx%+mv;@OMn3ld": {"opcode": "motion_pointindirection", "next": "I0{bBzf`prP}2Nszk[J}", "parent": "/8H/QPflcfn0ek?VmU+l", "inputs": {"DIRECTION": [1, [8, "90"]]}, "fields": {}, "shadow": false, "topLevel": false}, "I0{bBzf`prP}2Nszk[J}": {"opcode": "looks_switchcostumeto", "next": "F69niIKe=Vt_%R)%ro!0", "parent": "-7aR[iFx%+mv;@OMn3ld", "inputs": {"COSTUME": [1, "X_%0Cin?;V,T=F6:qew5"]}, "fields": {}, "shadow": false, "topLevel": false}, "X_%0Cin?;V,T=F6:qew5": {"opcode": "looks_costume", "next": null, "parent": "I0{bBzf`prP}2Nszk[J}", "inputs": {}, "fields": {"COSTUME": ["\u53f3\u4fa7", null]}, "shadow": true, "topLevel": false}, "F69niIKe=Vt_%R)%ro!0": {"opcode": "motion_movesteps", "next": null, "parent": "I0{bBzf`prP}2Nszk[J}", "inputs": {"STEPS": [1, [4, "10"]]}, "fields": {}, "shadow": false, "topLevel": false}}, "comments": {}, "currentCostume": 0, "costumes": [{"assetId": "6d5c2f4220d31d77923556ddadbe2cb7", "name": "\u6b63\u9762", "bitmapResolution": 2, "md5ext": "6d5c2f4220d31d77923556ddadbe2cb7.png", "dataFormat": "png", "rotationCenterX": 408, "rotationCenterY": 306}, {"assetId": "5500fa153f15ad0654b9b5ee5e8cb60b", "name": "\u80cc\u9762", "bitmapResolution": 2, "md5ext": "5500fa153f15ad0654b9b5ee5e8cb60b.png", "dataFormat": "png", "rotationCenterX": 408, "rotationCenterY": 306}, {"assetId": "75704083eb3f861c7ab4446f146fa210", "name": "\u5de6\u4fa7", "bitmapResolution": 2, "md5ext": "75704083eb3f861c7ab4446f146fa210.png", "dataFormat": "png", "rotationCenterX": 408, "rotationCenterY": 306}, {"assetId": "0ae758003b05092e479bcc28ef18a68a", "name": "\u53f3\u4fa7", "bitmapResolution": 2, "md5ext": "0ae758003b05092e479bcc28ef18a68a.png", "dataFormat": "png", "rotationCenterX": 408, "rotationCenterY": 306}], "sounds": [], "volume": 100, "layerOrder": 1, "visible": true, "x": -175, "y": -63, "size": 100, "direction": 180, "draggable": false, "rotationStyle": "don't rotate"}, {"isStage": false, "name": "\u65b9\u5757\u517d\u738b", "variables": {}, "lists": {}, "broadcasts": {}, "blocks": {"@|Ku-;14~P0S#XXpXKYf": {"opcode": "motion_gotoxy", "next": "JArgC`Wseyz!nP4uSbD$", "parent": "Bx8EBLCQ+qd?21p:o(m$", "inputs": {"X": [1, [4, "208"]], "Y": [1, [4, "106"]]}, "fields": {}, "shadow": false, "topLevel": false}, "F.B)xRW2x;@FH8R!?4Um": {"opcode": "event_whenflagclicked", "next": "Bx8EBLCQ+qd?21p:o(m$", "parent": null, "inputs": {}, "fields": {}, "shadow": false, "topLevel": true, "x": 7, "y": 27}, "JArgC`Wseyz!nP4uSbD$": {"opcode": "control_forever", "next": null, "parent": "@|Ku-;14~P0S#XXpXKYf", "inputs": {"SUBSTACK": [2, "}|Qz=2uObtdl51Aa|9QK"]}, "fields": {}, "shadow": false, "topLevel": false}, "3teGI30O5XHSe(kn6)`=": {"opcode": "motion_movesteps", "next": "O(wyl9s61.WQg#2Levz-", "parent": "cwK/,Oe}XLUKD0wfXDY-", "inputs": {"STEPS": [1, [4, "1"]]}, "fields": {}, "shadow": false, "topLevel": false}, "cwK/,Oe}XLUKD0wfXDY-": {"opcode": "motion_pointtowards", "next": "3teGI30O5XHSe(kn6)`=", "parent": "}|Qz=2uObtdl51Aa|9QK", "inputs": {"TOWARDS": [1, "9!@S{sd1Vt(zK14}rgUX"]}, "fields": {}, "shadow": false, "topLevel": false}, "9!@S{sd1Vt(zK14}rgUX": {"opcode": "motion_pointtowards_menu", "next": null, "parent": "cwK/,Oe}XLUKD0wfXDY-", "inputs": {}, "fields": {"TOWARDS": ["\u6bd4\u5c14", null]}, "shadow": true, "topLevel": false}, "O(wyl9s61.WQg#2Levz-": {"opcode": "control_if", "next": "w}mNZ)MTlO$2v_HSORhD", "parent": "3teGI30O5XHSe(kn6)`=", "inputs": {"CONDITION": [2, "VWaqG^gWkB#kRXV-{MJV"], "SUBSTACK": [2, "z8S3(=R%sw!}6@trlD~V"]}, "fields": {}, "shadow": false, "topLevel": false}, "VWaqG^gWkB#kRXV-{MJV": {"opcode": "sensing_touchingobject", "next": null, "parent": "O(wyl9s61.WQg#2Levz-", "inputs": {"TOUCHINGOBJECTMENU": [1, "V!F9w[6PQeVU|IWTF%A@"]}, "fields": {}, "shadow": false, "topLevel": false}, "V!F9w[6PQeVU|IWTF%A@": {"opcode": "sensing_touchingobjectmenu", "next": null, "parent": "VWaqG^gWkB#kRXV-{MJV", "inputs": {}, "fields": {"TOUCHINGOBJECTMENU": ["\u6bd4\u5c14", null]}, "shadow": true, "topLevel": false}, "z8S3(=R%sw!}6@trlD~V": {"opcode": "control_stop", "next": null, "parent": "O(wyl9s61.WQg#2Levz-", "inputs": {}, "fields": {"STOP_OPTION": ["all", null]}, "shadow": false, "topLevel": false, "mutation": {"tagName": "mutation", "children": [], "hasnext": "false"}}, "}|Qz=2uObtdl51Aa|9QK": {"opcode": "motion_pointindirection", "next": "cwK/,Oe}XLUKD0wfXDY-", "parent": "JArgC`Wseyz!nP4uSbD$", "inputs": {"DIRECTION": [1, [8, "90"]]}, "fields": {}, "shadow": false, "topLevel": false}, "U|.nL+cNHVqYwa)N}kG0": {"opcode": "looks_hide", "next": null, "parent": "w}mNZ)MTlO$2v_HSORhD", "inputs": {}, "fields": {}, "shadow": false, "topLevel": false}, "Bx8EBLCQ+qd?21p:o(m$": {"opcode": "looks_show", "next": "@|Ku-;14~P0S#XXpXKYf", "parent": "F.B)xRW2x;@FH8R!?4Um", "inputs": {}, "fields": {}, "shadow": false, "topLevel": false}, "w}mNZ)MTlO$2v_HSORhD": {"opcode": "control_if", "next": null, "parent": "O(wyl9s61.WQg#2Levz-", "inputs": {"CONDITION": [2, "Vtwz~/8Rda1HjQ-L[G-n"], "SUBSTACK": [2, "U|.nL+cNHVqYwa)N}kG0"]}, "fields": {}, "shadow": false, "topLevel": false}, "Vtwz~/8Rda1HjQ-L[G-n": {"opcode": "sensing_touchingobject", "next": null, "parent": "w}mNZ)MTlO$2v_HSORhD", "inputs": {"TOUCHINGOBJECTMENU": [1, "8P|TYHzuN3d,)$~YLdt/"]}, "fields": {}, "shadow": false, "topLevel": false}, "8P|TYHzuN3d,)$~YLdt/": {"opcode": "sensing_touchingobjectmenu", "next": null, "parent": "Vtwz~/8Rda1HjQ-L[G-n", "inputs": {}, "fields": {"TOUCHINGOBJECTMENU": ["\u6b66\u5668", null]}, "shadow": true, "topLevel": false}}, "comments": {}, "currentCostume": 0, "costumes": [{"assetId": "793671f9aa1603ca2a25673a08dbb2f9", "name": "\u65b9\u5757\u517d", "bitmapResolution": 1, "md5ext": "793671f9aa1603ca2a25673a08dbb2f9.svg", "dataFormat": "svg", "rotationCenterX": 16, "rotationCenterY": 23}], "sounds": [], "volume": 100, "layerOrder": 5, "visible": false, "x": -175.00135092746095, "y": -62.33090488181699, "size": 333, "direction": -0.11568211254292748, "draggable": false, "rotationStyle": "left-right"}, {"isStage": false, "name": "\u65b9\u5757\u517d2", "variables": {}, "lists": {}, "broadcasts": {}, "blocks": {"G[UI{s*x7bYN}+{sKffS": {"opcode": "motion_gotoxy", "next": "#nmnCbaNz870|3R*7F^y", "parent": "]JxthgmSq}P=cViplWSF", "inputs": {"X": [1, [4, "211"]], "Y": [1, [4, "147"]]}, "fields": {}, "shadow": false, "topLevel": false}, "E.HM?EhG5yL{OC6fe+B%": {"opcode": "event_whenflagclicked", "next": "]JxthgmSq}P=cViplWSF", "parent": null, "inputs": {}, "fields": {}, "shadow": false, "topLevel": true, "x": 91, "y": 207}, "#nmnCbaNz870|3R*7F^y": {"opcode": "control_forever", "next": null, "parent": "G[UI{s*x7bYN}+{sKffS", "inputs": {"SUBSTACK": [3, "t[zHeOYSh2GPJ*A)i%K=", null]}, "fields": {}, "shadow": false, "topLevel": false}, "s~`-~DnJe`C3{wx|RIE/": {"opcode": "motion_movesteps", "next": "qAe8%{_SQx6/K:|*8JE^", "parent": "+piqi:wPcnvC`Bm,dE+X", "inputs": {"STEPS": [1, [4, "2"]]}, "fields": {}, "shadow": false, "topLevel": false}, "+piqi:wPcnvC`Bm,dE+X": {"opcode": "motion_pointtowards", "next": "s~`-~DnJe`C3{wx|RIE/", "parent": "t[zHeOYSh2GPJ*A)i%K=", "inputs": {"TOWARDS": [1, "!eS1DM@,X%S|#X3WF`({"]}, "fields": {}, "shadow": false, "topLevel": false}, "!eS1DM@,X%S|#X3WF`({": {"opcode": "motion_pointtowards_menu", "next": null, "parent": "+piqi:wPcnvC`Bm,dE+X", "inputs": {}, "fields": {"TOWARDS": ["\u6bd4\u5c14", null]}, "shadow": true, "topLevel": false}, "qAe8%{_SQx6/K:|*8JE^": {"opcode": "control_if", "next": "zL6dO/)3*h/`wbDKBpVV", "parent": "s~`-~DnJe`C3{wx|RIE/", "inputs": {"CONDITION": [3, "PC54/-Fko~[@Mr=hl1ST", null], "SUBSTACK": [3, "jTU9mz*X{jcFtKdOzGVM", null]}, "fields": {}, "shadow": false, "topLevel": false}, "PC54/-Fko~[@Mr=hl1ST": {"opcode": "sensing_touchingobject", "next": null, "parent": "qAe8%{_SQx6/K:|*8JE^", "inputs": {"TOUCHINGOBJECTMENU": [1, "xTbpRtVZ-[PPL1/Hp4df"]}, "fields": {}, "shadow": false, "topLevel": false}, "xTbpRtVZ-[PPL1/Hp4df": {"opcode": "sensing_touchingobjectmenu", "next": null, "parent": "PC54/-Fko~[@Mr=hl1ST", "inputs": {}, "fields": {"TOUCHINGOBJECTMENU": ["\u6bd4\u5c14", null]}, "shadow": true, "topLevel": false}, "jTU9mz*X{jcFtKdOzGVM": {"opcode": "control_stop", "next": null, "parent": "qAe8%{_SQx6/K:|*8JE^", "inputs": {}, "fields": {"STOP_OPTION": ["all", null]}, "shadow": false, "topLevel": false, "mutation": {"tagName": "mutation", "children": [], "hasnext": "false"}}, "t[zHeOYSh2GPJ*A)i%K=": {"opcode": "motion_pointindirection", "next": "+piqi:wPcnvC`Bm,dE+X", "parent": "#nmnCbaNz870|3R*7F^y", "inputs": {"DIRECTION": [1, [8, "90"]]}, "fields": {}, "shadow": false, "topLevel": false}, "X|N*3l{.~dJRQ,E7Q7Nr": {"opcode": "looks_hide", "next": null, "parent": "zL6dO/)3*h/`wbDKBpVV", "inputs": {}, "fields": {}, "shadow": false, "topLevel": false}, "]JxthgmSq}P=cViplWSF": {"opcode": "looks_show", "next": "G[UI{s*x7bYN}+{sKffS", "parent": "E.HM?EhG5yL{OC6fe+B%", "inputs": {}, "fields": {}, "shadow": false, "topLevel": false}, "zL6dO/)3*h/`wbDKBpVV": {"opcode": "control_if", "next": null, "parent": "qAe8%{_SQx6/K:|*8JE^", "inputs": {"CONDITION": [3, ").%q~0cD}%^I)5+Lj{7(", null], "SUBSTACK": [3, "X|N*3l{.~dJRQ,E7Q7Nr", null]}, "fields": {}, "shadow": false, "topLevel": false}, ").%q~0cD}%^I)5+Lj{7(": {"opcode": "sensing_touchingobject", "next": null, "parent": "zL6dO/)3*h/`wbDKBpVV", "inputs": {"TOUCHINGOBJECTMENU": [1, "6G6~V]tRjkG-tSO#Jl7."]}, "fields": {}, "shadow": false, "topLevel": false}, "6G6~V]tRjkG-tSO#Jl7.": {"opcode": "sensing_touchingobjectmenu", "next": null, "parent": ").%q~0cD}%^I)5+Lj{7(", "inputs": {}, "fields": {"TOUCHINGOBJECTMENU": ["\u6b66\u5668"]}, "shadow": true, "topLevel": false}}, "comments": {}, "currentCostume": 0, "costumes": [{"assetId": "793671f9aa1603ca2a25673a08dbb2f9", "name": "\u65b9\u5757\u517d", "bitmapResolution": 1, "md5ext": "793671f9aa1603ca2a25673a08dbb2f9.svg", "dataFormat": "svg", "rotationCenterX": 16, "rotationCenterY": 23}], "sounds": [], "volume": 100, "layerOrder": 4, "visible": false, "x": -175.1772181311558, "y": -64.55348364916638, "size": 100, "direction": -173.4919526646272, "draggable": false, "rotationStyle": "left-right"}, {"isStage": false, "name": "\u65b9\u5757\u517d3", "variables": {}, "lists": {}, "broadcasts": {}, "blocks": {"9H!H1q%9k[WDmP(:EXS?": {"opcode": "motion_gotoxy", "next": "]Z!uL8k^Y)79kHY54^Pn", "parent": "/q[8Wz-xKLm3aM9g;@B,", "inputs": {"X": [1, [4, "114"]], "Y": [1, [4, "140"]]}, "fields": {}, "shadow": false, "topLevel": false}, "{x0*R0-s=_/~l6l|k!3I": {"opcode": "event_whenflagclicked", "next": "/q[8Wz-xKLm3aM9g;@B,", "parent": null, "inputs": {}, "fields": {}, "shadow": false, "topLevel": true, "x": 30, "y": 65}, "]Z!uL8k^Y)79kHY54^Pn": {"opcode": "control_forever", "next": null, "parent": "9H!H1q%9k[WDmP(:EXS?", "inputs": {"SUBSTACK": [3, "]Wlg9r4fC}2)2L`8z_ld", null]}, "fields": {}, "shadow": false, "topLevel": false}, "2TWU[1WuQ`K-3:6l/{Oq": {"opcode": "motion_movesteps", "next": "gb8}W0%53ipQjJkuPMib", "parent": "_Pm32SzL|SAV=CaLRoIa", "inputs": {"STEPS": [1, [4, "2"]]}, "fields": {}, "shadow": false, "topLevel": false}, "_Pm32SzL|SAV=CaLRoIa": {"opcode": "motion_pointtowards", "next": "2TWU[1WuQ`K-3:6l/{Oq", "parent": "]Wlg9r4fC}2)2L`8z_ld", "inputs": {"TOWARDS": [1, "![nP_=]k,nS/Du@oB;H^"]}, "fields": {}, "shadow": false, "topLevel": false}, "![nP_=]k,nS/Du@oB;H^": {"opcode": "motion_pointtowards_menu", "next": null, "parent": "_Pm32SzL|SAV=CaLRoIa", "inputs": {}, "fields": {"TOWARDS": ["\u6bd4\u5c14", null]}, "shadow": true, "topLevel": false}, "gb8}W0%53ipQjJkuPMib": {"opcode": "control_if", "next": "q(W3Uf#]dx-7.vCWMwJa", "parent": "2TWU[1WuQ`K-3:6l/{Oq", "inputs": {"CONDITION": [3, "IFi[9e3v~g`WveF7A9dk", null], "SUBSTACK": [3, "H}w9r[J=Ow^;rq|SRXaM", null]}, "fields": {}, "shadow": false, "topLevel": false}, "IFi[9e3v~g`WveF7A9dk": {"opcode": "sensing_touchingobject", "next": null, "parent": "gb8}W0%53ipQjJkuPMib", "inputs": {"TOUCHINGOBJECTMENU": [1, "jMb6#ktT_qO+@ZjZg3I?"]}, "fields": {}, "shadow": false, "topLevel": false}, "jMb6#ktT_qO+@ZjZg3I?": {"opcode": "sensing_touchingobjectmenu", "next": null, "parent": "IFi[9e3v~g`WveF7A9dk", "inputs": {}, "fields": {"TOUCHINGOBJECTMENU": ["\u6bd4\u5c14", null]}, "shadow": true, "topLevel": false}, "H}w9r[J=Ow^;rq|SRXaM": {"opcode": "control_stop", "next": null, "parent": "gb8}W0%53ipQjJkuPMib", "inputs": {}, "fields": {"STOP_OPTION": ["all", null]}, "shadow": false, "topLevel": false, "mutation": {"tagName": "mutation", "children": [], "hasnext": "false"}}, "]Wlg9r4fC}2)2L`8z_ld": {"opcode": "motion_pointindirection", "next": "_Pm32SzL|SAV=CaLRoIa", "parent": "]Z!uL8k^Y)79kHY54^Pn", "inputs": {"DIRECTION": [1, [8, "90"]]}, "fields": {}, "shadow": false, "topLevel": false}, "eE9{8?f|mDTQ.Lw(PL^z": {"opcode": "looks_hide", "next": null, "parent": "q(W3Uf#]dx-7.vCWMwJa", "inputs": {}, "fields": {}, "shadow": false, "topLevel": false}, "/q[8Wz-xKLm3aM9g;@B,": {"opcode": "looks_show", "next": "9H!H1q%9k[WDmP(:EXS?", "parent": "{x0*R0-s=_/~l6l|k!3I", "inputs": {}, "fields": {}, "shadow": false, "topLevel": false}, "q(W3Uf#]dx-7.vCWMwJa": {"opcode": "control_if", "next": null, "parent": "gb8}W0%53ipQjJkuPMib", "inputs": {"CONDITION": [3, "T8e7pY32A_5pp*+MQX}T", null], "SUBSTACK": [3, "eE9{8?f|mDTQ.Lw(PL^z", null]}, "fields": {}, "shadow": false, "topLevel": false}, "T8e7pY32A_5pp*+MQX}T": {"opcode": "sensing_touchingobject", "next": null, "parent": "q(W3Uf#]dx-7.vCWMwJa", "inputs": {"TOUCHINGOBJECTMENU": [1, "H.MB^CS2[Ubdx7:j}o,t"]}, "fields": {}, "shadow": false, "topLevel": false}, "H.MB^CS2[Ubdx7:j}o,t": {"opcode": "sensing_touchingobjectmenu", "next": null, "parent": "T8e7pY32A_5pp*+MQX}T", "inputs": {}, "fields": {"TOUCHINGOBJECTMENU": ["\u6b66\u5668"]}, "shadow": true, "topLevel": false}}, "comments": {}, "currentCostume": 0, "costumes": [{"assetId": "793671f9aa1603ca2a25673a08dbb2f9", "name": "\u65b9\u5757\u517d", "bitmapResolution": 1, "md5ext": "793671f9aa1603ca2a25673a08dbb2f9.svg", "dataFormat": "svg", "rotationCenterX": 16, "rotationCenterY": 23}], "sounds": [], "volume": 100, "layerOrder": 6, "visible": false, "x": -175.1772181311558, "y": -64.55348364916638, "size": 100, "direction": -173.4919526646272, "draggable": false, "rotationStyle": "left-right"}, {"isStage": false, "name": "\u65b9\u5757\u517d4", "variables": {}, "lists": {}, "broadcasts": {}, "blocks": {"8vH^9%|eGJMt%!o^H#3t": {"opcode": "motion_gotoxy", "next": "5!{|9-r%J8y?U36[R%6X", "parent": "VCuLzaR6C:FSM3McM#.v", "inputs": {"X": [1, [4, "99"]], "Y": [1, [4, "101"]]}, "fields": {}, "shadow": false, "topLevel": false}, "q,xh0!lHho]Osu6Vvr}%": {"opcode": "event_whenflagclicked", "next": "VCuLzaR6C:FSM3McM#.v", "parent": null, "inputs": {}, "fields": {}, "shadow": false, "topLevel": true, "x": 30, "y": 65}, "5!{|9-r%J8y?U36[R%6X": {"opcode": "control_forever", "next": null, "parent": "8vH^9%|eGJMt%!o^H#3t", "inputs": {"SUBSTACK": [3, "9lh,YEFpBZNQ;(O?=[V2", null]}, "fields": {}, "shadow": false, "topLevel": false}, "d_.LLo+QZU;}m+mO/9XK": {"opcode": "motion_movesteps", "next": "+=lvSTS}o1T_aarH!Z*0", "parent": "Q+m*Kc(U:4%uKZ%BaJWX", "inputs": {"STEPS": [1, [4, "2"]]}, "fields": {}, "shadow": false, "topLevel": false}, "Q+m*Kc(U:4%uKZ%BaJWX": {"opcode": "motion_pointtowards", "next": "d_.LLo+QZU;}m+mO/9XK", "parent": "9lh,YEFpBZNQ;(O?=[V2", "inputs": {"TOWARDS": [1, "ql:qS(fu5[)2pZ%b}THS"]}, "fields": {}, "shadow": false, "topLevel": false}, "ql:qS(fu5[)2pZ%b}THS": {"opcode": "motion_pointtowards_menu", "next": null, "parent": "Q+m*Kc(U:4%uKZ%BaJWX", "inputs": {}, "fields": {"TOWARDS": ["\u6bd4\u5c14", null]}, "shadow": true, "topLevel": false}, "+=lvSTS}o1T_aarH!Z*0": {"opcode": "control_if", "next": "WJ9p=7D1O[X?|A8SNl2e", "parent": "d_.LLo+QZU;}m+mO/9XK", "inputs": {"CONDITION": [3, "%A%Bus35-Km[mXeb22)Q", null], "SUBSTACK": [3, "8Zm.X%(}Uy[X+f?X,USy", null]}, "fields": {}, "shadow": false, "topLevel": false}, "%A%Bus35-Km[mXeb22)Q": {"opcode": "sensing_touchingobject", "next": null, "parent": "+=lvSTS}o1T_aarH!Z*0", "inputs": {"TOUCHINGOBJECTMENU": [1, "E9Uk6`~F)wmeWd7a-c11"]}, "fields": {}, "shadow": false, "topLevel": false}, "E9Uk6`~F)wmeWd7a-c11": {"opcode": "sensing_touchingobjectmenu", "next": null, "parent": "%A%Bus35-Km[mXeb22)Q", "inputs": {}, "fields": {"TOUCHINGOBJECTMENU": ["\u6bd4\u5c14", null]}, "shadow": true, "topLevel": false}, "8Zm.X%(}Uy[X+f?X,USy": {"opcode": "control_stop", "next": null, "parent": "+=lvSTS}o1T_aarH!Z*0", "inputs": {}, "fields": {"STOP_OPTION": ["all", null]}, "shadow": false, "topLevel": false, "mutation": {"tagName": "mutation", "children": [], "hasnext": "false"}}, "9lh,YEFpBZNQ;(O?=[V2": {"opcode": "motion_pointindirection", "next": "Q+m*Kc(U:4%uKZ%BaJWX", "parent": "5!{|9-r%J8y?U36[R%6X", "inputs": {"DIRECTION": [1, [8, "90"]]}, "fields": {}, "shadow": false, "topLevel": false}, "IQI1Udk3%5OdVUyqyq81": {"opcode": "looks_hide", "next": null, "parent": "WJ9p=7D1O[X?|A8SNl2e", "inputs": {}, "fields": {}, "shadow": false, "topLevel": false}, "VCuLzaR6C:FSM3McM#.v": {"opcode": "looks_show", "next": "8vH^9%|eGJMt%!o^H#3t", "parent": "q,xh0!lHho]Osu6Vvr}%", "inputs": {}, "fields": {}, "shadow": false, "topLevel": false}, "WJ9p=7D1O[X?|A8SNl2e": {"opcode": "control_if", "next": null, "parent": "+=lvSTS}o1T_aarH!Z*0", "inputs": {"CONDITION": [3, "=.kmtoZZ*E1VQmO[u/wK", null], "SUBSTACK": [3, "IQI1Udk3%5OdVUyqyq81", null]}, "fields": {}, "shadow": false, "topLevel": false}, "=.kmtoZZ*E1VQmO[u/wK": {"opcode": "sensing_touchingobject", "next": null, "parent": "WJ9p=7D1O[X?|A8SNl2e", "inputs": {"TOUCHINGOBJECTMENU": [1, "p||~N!_gdO0nWp25SQb,"]}, "fields": {}, "shadow": false, "topLevel": false}, "p||~N!_gdO0nWp25SQb,": {"opcode": "sensing_touchingobjectmenu", "next": null, "parent": "=.kmtoZZ*E1VQmO[u/wK", "inputs": {}, "fields": {"TOUCHINGOBJECTMENU": ["\u6b66\u5668"]}, "shadow": true, "topLevel": false}}, "comments": {}, "currentCostume": 0, "costumes": [{"assetId": "793671f9aa1603ca2a25673a08dbb2f9", "name": "\u65b9\u5757\u517d", "bitmapResolution": 1, "md5ext": "793671f9aa1603ca2a25673a08dbb2f9.svg", "dataFormat": "svg", "rotationCenterX": 16, "rotationCenterY": 23}], "sounds": [], "volume": 100, "layerOrder": 3, "visible": false, "x": -175.1772181311558, "y": -64.55348364916638, "size": 100, "direction": -173.4919526646272, "draggable": false, "rotationStyle": "left-right"}], "monitors": [], "extensions": [], "meta": {"semver": "3.0.0", "vm": "0.2.0-prerelease.20190524155459", "agent": "Mozilla/5.0 (Windows NT 6.1; WOW64) AppleWebKit/537.36 (KHTML, like Gecko) Chrome/69.0.3497.100 Safari/537.36"}}