{"targets": [{"isStage": true, "name": "Stage", "variables": {}, "lists": {}, "broadcasts": {}, "blocks": {}, "comments": {}, "currentCostume": 0, "costumes": [{"assetId": "4f1a1e4e4d182393270fa1b546b7d902", "name": "\u65b9\u5757\u8349\u576a", "bitmapResolution": 2, "md5ext": "4f1a1e4e4d182393270fa1b546b7d902.png", "dataFormat": "png", "rotationCenterX": 480, "rotationCenterY": 360}], "sounds": [{"assetId": "83a9787d4cb6f3b7632b4ddfebf74367", "name": "\u5575", "dataFormat": "wav", "format": "", "rate": 48000, "sampleCount": 1123, "md5ext": "83a9787d4cb6f3b7632b4ddfebf74367.wav"}], "volume": 100, "layerOrder": 0, "tempo": 60, "videoTransparency": 50, "videoState": "off", "textToSpeechLanguage": null}, {"isStage": false, "name": "\u6bd4\u5c14", "variables": {}, "lists": {}, "broadcasts": {}, "blocks": {"EsUu:cU4B+UXZw2DgWqQ": {"opcode": "motion_gotoxy", "next": null, "parent": "Mca;;E~f*dYeAi3Dw81p", "inputs": {"X": [1, [4, "-152"]], "Y": [1, [4, "-146"]]}, "fields": {}, "shadow": false, "topLevel": false}, "Mca;;E~f*dYeAi3Dw81p": {"opcode": "event_whenflagclicked", "next": "EsUu:cU4B+UXZw2DgWqQ", "parent": null, "inputs": {}, "fields": {}, "shadow": false, "topLevel": true, "x": 352, "y": 382}}, "comments": {}, "currentCostume": 0, "costumes": [{"assetId": "6d5c2f4220d31d77923556ddadbe2cb7", "name": "\u6b63\u9762", "bitmapResolution": 2, "md5ext": "6d5c2f4220d31d77923556ddadbe2cb7.png", "dataFormat": "png", "rotationCenterX": 408, "rotationCenterY": 306}, {"assetId": "5500fa153f15ad0654b9b5ee5e8cb60b", "name": "\u80cc\u9762", "bitmapResolution": 2, "md5ext": "5500fa153f15ad0654b9b5ee5e8cb60b.png", "dataFormat": "png", "rotationCenterX": 408, "rotationCenterY": 306}, {"assetId": "75704083eb3f861c7ab4446f146fa210", "name": "\u5de6\u4fa7", "bitmapResolution": 2, "md5ext": "75704083eb3f861c7ab4446f146fa210.png", "dataFormat": "png", "rotationCenterX": 408, "rotationCenterY": 306}, {"assetId": "0ae758003b05092e479bcc28ef18a68a", "name": "\u53f3\u4fa7", "bitmapResolution": 2, "md5ext": "0ae758003b05092e479bcc28ef18a68a.png", "dataFormat": "png", "rotationCenterX": 408, "rotationCenterY": 306}], "sounds": [], "volume": 100, "layerOrder": 1, "visible": true, "x": -152, "y": -146, "size": 100, "direction": 48.91079688550281, "draggable": false, "rotationStyle": "all around"}, {"isStage": false, "name": "\u65b9\u5757\u517d", "variables": {}, "lists": {}, "broadcasts": {}, "blocks": {"#*:NeTWH7)ID~lu8|r6d": {"opcode": "motion_gotoxy", "next": ",C[j-bz7S7jU`$~HsWXM", "parent": "E/X7tLB0OIuZy=,pf]Fz", "inputs": {"X": [1, [4, "184"]], "Y": [1, [4, "147"]]}, "fields": {}, "shadow": false, "topLevel": false}, "E/X7tLB0OIuZy=,pf]Fz": {"opcode": "event_whenflagclicked", "next": "#*:NeTWH7)ID~lu8|r6d", "parent": null, "inputs": {}, "fields": {}, "shadow": false, "topLevel": true, "x": 531, "y": 47}, ",C[j-bz7S7jU`$~HsWXM": {"opcode": "control_forever", "next": null, "parent": "#*:NeTWH7)ID~lu8|r6d", "inputs": {"SUBSTACK": [2, "E$qap1,YdKeh,jj$VyFE"]}, "fields": {}, "shadow": false, "topLevel": false}, "UMuWl?}rXQ5-dQ27y2q+": {"opcode": "motion_movesteps", "next": "Rn@%H3i,c3M@+OVbr,ef", "parent": "E$qap1,YdKeh,jj$VyFE", "inputs": {"STEPS": [1, [4, "2"]]}, "fields": {}, "shadow": false, "topLevel": false}, "E$qap1,YdKeh,jj$VyFE": {"opcode": "motion_pointtowards", "next": "UMuWl?}rXQ5-dQ27y2q+", "parent": ",C[j-bz7S7jU`$~HsWXM", "inputs": {"TOWARDS": [1, "IpsOar0b_w?VK{j~*Rqw"]}, "fields": {}, "shadow": false, "topLevel": false}, "IpsOar0b_w?VK{j~*Rqw": {"opcode": "motion_pointtowards_menu", "next": null, "parent": "E$qap1,YdKeh,jj$VyFE", "inputs": {}, "fields": {"TOWARDS": ["\u6bd4\u5c14", null]}, "shadow": true, "topLevel": false}, "Rn@%H3i,c3M@+OVbr,ef": {"opcode": "control_if", "next": null, "parent": "UMuWl?}rXQ5-dQ27y2q+", "inputs": {"CONDITION": [2, "8|*LFRQcedMPOgoz=y6("], "SUBSTACK": [2, "-l*lnfzm[FZT#D@XAzT."]}, "fields": {}, "shadow": false, "topLevel": false}, "8|*LFRQcedMPOgoz=y6(": {"opcode": "sensing_touchingobject", "next": null, "parent": "Rn@%H3i,c3M@+OVbr,ef", "inputs": {"TOUCHINGOBJECTMENU": [1, "J+].fS09eb!GvQd$3l3~"]}, "fields": {}, "shadow": false, "topLevel": false}, "J+].fS09eb!GvQd$3l3~": {"opcode": "sensing_touchingobjectmenu", "next": null, "parent": "8|*LFRQcedMPOgoz=y6(", "inputs": {}, "fields": {"TOUCHINGOBJECTMENU": ["\u6bd4\u5c14", null]}, "shadow": true, "topLevel": false}, "-l*lnfzm[FZT#D@XAzT.": {"opcode": "control_stop", "next": null, "parent": "Rn@%H3i,c3M@+OVbr,ef", "inputs": {}, "fields": {"STOP_OPTION": ["all", null]}, "shadow": false, "topLevel": false, "mutation": {"tagName": "mutation", "children": [], "hasnext": "false"}}}, "comments": {}, "currentCostume": 0, "costumes": [{"assetId": "793671f9aa1603ca2a25673a08dbb2f9", "name": "\u65b9\u5757\u517d", "bitmapResolution": 1, "md5ext": "793671f9aa1603ca2a25673a08dbb2f9.svg", "dataFormat": "svg", "rotationCenterX": 16, "rotationCenterY": 23}], "sounds": [], "volume": 100, "layerOrder": 2, "visible": true, "x": -138.57814535492906, "y": -134.2958231815303, "size": 100, "direction": -131.0892031144974, "draggable": false, "rotationStyle": "left-right"}], "monitors": [], "extensions": [], "meta": {"semver": "3.0.0", "vm": "0.2.0-prerelease.20190524155459", "agent": "Mozilla/5.0 (Windows NT 6.2; WOW64) AppleWebKit/537.36 (KHTML, like Gecko) Chrome/70.0.3538.25 Safari/537.36 Core/1.70.3704.400 QQBrowser/10.4.3587.400"}}